pypssfss/__init__.py
pypssfss/py.typed
pypssfss/pypssfss.py
pypssfss/sheets.py
pypssfss/steering.py
pypssfss-0.1.0.dist-info/METADATA
pypssfss-0.1.0.dist-info/WHEEL
pypssfss-0.1.0.dist-info/licenses/LICENSE
pypssfss-0.1.0.dist-info/RECORD
