Metadata-Version: 2.4
Name: pypssfss
Version: 0.1.0
Summary: Python wrapper for Julia package PSSFSS - Analysis of Polarization and Frequency Selective Surfaces
Author-email: Peter Simon <psimon0420@gmail.com>
License-File: LICENSE
Keywords: FSS,Frequency Selective Surface,Julia,PSSFSS,Polarization Selective Surface,RF,antenna,computational electromagnetics,electromagnetics,metasurface,microwave,python
Classifier: Development Status :: 4 - Beta
Classifier: Intended Audience :: Science/Research
Classifier: Operating System :: MacOS :: MacOS X
Classifier: Operating System :: Microsoft :: Windows
Classifier: Operating System :: POSIX :: Linux
Classifier: Programming Language :: Python :: 3
Requires-Python: >=3.10
Requires-Dist: juliacall~=0.9.24
Requires-Dist: juliapkg~=0.1.16
Requires-Dist: matplotlib~=3.9
Requires-Dist: numpy~=2.0
Requires-Dist: rich~=14.0.0
